euclidsturtle/__init__.py
euclidsturtle/geotool.py
euclidsturtle/turtle.py
euclidsturtle-1.1.1.dist-info/LICENSE
euclidsturtle-1.1.1.dist-info/METADATA
euclidsturtle-1.1.1.dist-info/WHEEL
euclidsturtle-1.1.1.dist-info/top_level.txt
euclidsturtle-1.1.1.dist-info/RECORD
